<?xml version="1.0" encoding="UTF-8" standalone="no"?><Snake><Position><X>5.0</X><Y>19.0</Y></Position><Food><fX>11.0</fX><fY>4.0</fY></Food><Score>0</Score><Direction>UP</Direction><Position><X>5.0</X><Y>19.0</Y></Position><Food><fX>11.0</fX><fY>4.0</fY></Food><Score>0</Score><Direction>UP</Direction><Position><X>5.0</X><Y>18.0</Y></Position><Food><fX>11.0</fX><fY>4.0</fY></Food><Score>0</Score><Direction>UP</Direction><Position><X>5.0</X><Y>17.0</Y></Position><Food><fX>11.0</fX><fY>4.0</fY></Food><Score>0</Score><Direction>RIGHT</Direction><Position><X>5.0</X><Y>16.0</Y></Position><Food><fX>11.0</fX><fY>4.0</fY></Food><Score>0</Score><Direction>UP</Direction><Position><X>6.0</X><Y>16.0</Y></Position><Food><fX>11.0</fX><fY>4.0</fY></Food><Score>0</Score><Direction>UP</Direction><Position><X>6.0</X><Y>15.0</Y></Position><Food><fX>11.0</fX><fY>4.0</fY></Food><Score>0</Score><Direction>LEFT</Direction><Position><X>6.0</X><Y>14.0</Y></Position><Food><fX>11.0</fX><fY>4.0</fY></Food><Score>0</Score><Direction>LEFT</Direction><Position><X>5.0</X><Y>14.0</Y></Position><Food><fX>11.0</fX><fY>4.0</fY></Food><Score>0</Score><Direction>LEFT</Direction><Position><X>4.0</X><Y>14.0</Y></Position><Food><fX>11.0</fX><fY>4.0</fY></Food><Score>0</Score><Direction>LEFT</Direction><Position><X>3.0</X><Y>14.0</Y></Position><Food><fX>11.0</fX><fY>4.0</fY></Food><Score>0</Score><Direction>LEFT</Direction><Position><X>2.0</X><Y>14.0</Y></Position><Food><fX>11.0</fX><fY>4.0</fY></Food><Score>0</Score><Direction>LEFT</Direction><Position><X>1.0</X><Y>14.0</Y></Position><Food><fX>11.0</fX><fY>4.0</fY></Food><Score>0</Score><Direction>LEFT</Direction></Snake>