<?xml version="1.0" encoding="UTF-8" standalone="no"?><Snake><Position><X>5.0</X><Y>19.0</Y></Position><Food><fX>4.0</fX><fY>11.0</fY></Food><Score>0</Score><Direction>UP</Direction><Position><X>5.0</X><Y>19.0</Y></Position><Food><fX>4.0</fX><fY>11.0</fY></Food><Score>0</Score><Direction>UP</Direction><Position><X>5.0</X><Y>18.0</Y></Position><Food><fX>4.0</fX><fY>11.0</fY></Food><Score>0</Score><Direction>UP</Direction><Position><X>5.0</X><Y>17.0</Y></Position><Food><fX>4.0</fX><fY>11.0</fY></Food><Score>0</Score><Direction>UP</Direction><Position><X>5.0</X><Y>16.0</Y></Position><Food><fX>4.0</fX><fY>11.0</fY></Food><Score>0</Score><Direction>LEFT</Direction><Position><X>5.0</X><Y>15.0</Y></Position><Food><fX>4.0</fX><fY>11.0</fY></Food><Score>0</Score><Direction>UP</Direction><Position><X>4.0</X><Y>15.0</Y></Position><Food><fX>4.0</fX><fY>11.0</fY></Food><Score>0</Score><Direction>UP</Direction><Position><X>4.0</X><Y>14.0</Y></Position><Food><fX>4.0</fX><fY>11.0</fY></Food><Score>0</Score><Direction>UP</Direction><Position><X>4.0</X><Y>13.0</Y></Position><Food><fX>4.0</fX><fY>11.0</fY></Food><Score>0</Score><Direction>UP</Direction><Position><X>4.0</X><Y>12.0</Y></Position><Food><fX>10.0</fX><fY>0.0</fY></Food><Score>0</Score><Direction>UP</Direction><Position><X>4.0</X><Y>11.0</Y></Position><Food><fX>10.0</fX><fY>0.0</fY></Food><Score>1</Score><Direction>RIGHT</Direction><Position><X>4.0</X><Y>10.0</Y></Position><Food><fX>10.0</fX><fY>0.0</fY></Food><Score>1</Score><Direction>RIGHT</Direction><Position><X>5.0</X><Y>10.0</Y></Position><Food><fX>10.0</fX><fY>0.0</fY></Food><Score>1</Score><Direction>RIGHT</Direction><Position><X>6.0</X><Y>10.0</Y></Position><Food><fX>10.0</fX><fY>0.0</fY></Food><Score>1</Score><Direction>RIGHT</Direction><Position><X>7.0</X><Y>10.0</Y></Position><Food><fX>10.0</fX><fY>0.0</fY></Food><Score>1</Score><Direction>RIGHT</Direction><Position><X>8.0</X><Y>10.0</Y></Position><Food><fX>10.0</fX><fY>0.0</fY></Food><Score>1</Score><Direction>RIGHT</Direction><Position><X>9.0</X><Y>10.0</Y></Position><Food><fX>10.0</fX><fY>0.0</fY></Food><Score>1</Score><Direction>RIGHT</Direction><Position><X>10.0</X><Y>10.0</Y></Position><Food><fX>10.0</fX><fY>0.0</fY></Food><Score>1</Score><Direction>RIGHT</Direction><Position><X>11.0</X><Y>10.0</Y></Position><Food><fX>10.0</fX><fY>0.0</fY></Food><Score>1</Score><Direction>RIGHT</Direction><Position><X>12.0</X><Y>10.0</Y></Position><Food><fX>10.0</fX><fY>0.0</fY></Food><Score>1</Score><Direction>RIGHT</Direction><Position><X>13.0</X><Y>10.0</Y></Position><Food><fX>10.0</fX><fY>0.0</fY></Food><Score>1</Score><Direction>RIGHT</Direction><Position><X>14.0</X><Y>10.0</Y></Position><Food><fX>10.0</fX><fY>0.0</fY></Food><Score>1</Score><Direction>RIGHT</Direction><Position><X>15.0</X><Y>10.0</Y></Position><Food><fX>10.0</fX><fY>0.0</fY></Food><Score>1</Score><Direction>RIGHT</Direction><Position><X>16.0</X><Y>10.0</Y></Position><Food><fX>10.0</fX><fY>0.0</fY></Food><Score>1</Score><Direction>RIGHT</Direction><Position><X>17.0</X><Y>10.0</Y></Position><Food><fX>10.0</fX><fY>0.0</fY></Food><Score>1</Score><Direction>RIGHT</Direction><Position><X>18.0</X><Y>10.0</Y></Position><Food><fX>10.0</fX><fY>0.0</fY></Food><Score>1</Score><Direction>RIGHT</Direction><Position><X>19.0</X><Y>10.0</Y></Position><Food><fX>11.0</fX><fY>10.0</fY></Food><Score>1</Score><Direction>RIGHT</Direction><Position><X>8.0</X><Y>10.0</Y></Position><Food><fX>11.0</fX><fY>10.0</fY></Food><Score>1</Score><Direction>RIGHT</Direction><Position><X>9.0</X><Y>10.0</Y></Position><Food><fX>11.0</fX><fY>10.0</fY></Food><Score>1</Score><Direction>RIGHT</Direction><Position><X>10.0</X><Y>10.0</Y></Position><Food><fX>7.0</fX><fY>2.0</fY></Food><Score>1</Score><Direction>RIGHT</Direction><Position><X>11.0</X><Y>10.0</Y></Position><Food><fX>7.0</fX><fY>2.0</fY></Food><Score>2</Score><Direction>RIGHT</Direction><Position><X>12.0</X><Y>10.0</Y></Position><Food><fX>7.0</fX><fY>2.0</fY></Food><Score>2</Score><Direction>RIGHT</Direction><Position><X>13.0</X><Y>10.0</Y></Position><Food><fX>7.0</fX><fY>2.0</fY></Food><Score>2</Score><Direction>RIGHT</Direction><Position><X>14.0</X><Y>10.0</Y></Position><Food><fX>7.0</fX><fY>2.0</fY></Food><Score>2</Score><Direction>UP</Direction><Position><X>15.0</X><Y>10.0</Y></Position><Food><fX>7.0</fX><fY>2.0</fY></Food><Score>2</Score><Direction>UP</Direction><Position><X>15.0</X><Y>9.0</Y></Position><Food><fX>7.0</fX><fY>2.0</fY></Food><Score>2</Score><Direction>UP</Direction><Position><X>15.0</X><Y>8.0</Y></Position><Food><fX>7.0</fX><fY>2.0</fY></Food><Score>2</Score><Direction>UP</Direction><Position><X>15.0</X><Y>7.0</Y></Position><Food><fX>7.0</fX><fY>2.0</fY></Food><Score>2</Score><Direction>UP</Direction><Position><X>15.0</X><Y>6.0</Y></Position><Food><fX>7.0</fX><fY>2.0</fY></Food><Score>2</Score><Direction>LEFT</Direction><Position><X>15.0</X><Y>5.0</Y></Position><Food><fX>7.0</fX><fY>2.0</fY></Food><Score>2</Score><Direction>LEFT</Direction><Position><X>14.0</X><Y>5.0</Y></Position><Food><fX>7.0</fX><fY>2.0</fY></Food><Score>2</Score><Direction>UP</Direction><Position><X>13.0</X><Y>5.0</Y></Position><Food><fX>7.0</fX><fY>2.0</fY></Food><Score>2</Score><Direction>UP</Direction><Position><X>13.0</X><Y>4.0</Y></Position><Food><fX>7.0</fX><fY>2.0</fY></Food><Score>2</Score><Direction>UP</Direction><Position><X>13.0</X><Y>3.0</Y></Position><Food><fX>7.0</fX><fY>2.0</fY></Food><Score>2</Score><Direction>LEFT</Direction><Position><X>13.0</X><Y>2.0</Y></Position><Food><fX>7.0</fX><fY>2.0</fY></Food><Score>2</Score><Direction>LEFT</Direction><Position><X>12.0</X><Y>2.0</Y></Position><Food><fX>7.0</fX><fY>2.0</fY></Food><Score>2</Score><Direction>LEFT</Direction><Position><X>11.0</X><Y>2.0</Y></Position><Food><fX>7.0</fX><fY>2.0</fY></Food><Score>2</Score><Direction>LEFT</Direction><Position><X>10.0</X><Y>2.0</Y></Position><Food><fX>7.0</fX><fY>2.0</fY></Food><Score>2</Score><Direction>LEFT</Direction><Position><X>9.0</X><Y>2.0</Y></Position><Food><fX>7.0</fX><fY>2.0</fY></Food><Score>2</Score><Direction>LEFT</Direction><Position><X>8.0</X><Y>2.0</Y></Position><Food><fX>16.0</fX><fY>16.0</fY></Food><Score>2</Score><Direction>LEFT</Direction><Position><X>7.0</X><Y>2.0</Y></Position><Food><fX>16.0</fX><fY>16.0</fY></Food><Score>3</Score><Direction>LEFT</Direction><Position><X>6.0</X><Y>2.0</Y></Position><Food><fX>16.0</fX><fY>16.0</fY></Food><Score>3</Score><Direction>DOWN</Direction><Position><X>5.0</X><Y>2.0</Y></Position><Food><fX>16.0</fX><fY>16.0</fY></Food><Score>3</Score><Direction>DOWN</Direction><Position><X>5.0</X><Y>3.0</Y></Position><Food><fX>16.0</fX><fY>16.0</fY></Food><Score>3</Score><Direction>DOWN</Direction><Position><X>5.0</X><Y>4.0</Y></Position><Food><fX>16.0</fX><fY>16.0</fY></Food><Score>3</Score><Direction>DOWN</Direction><Position><X>5.0</X><Y>5.0</Y></Position><Food><fX>16.0</fX><fY>16.0</fY></Food><Score>3</Score><Direction>DOWN</Direction><Position><X>5.0</X><Y>6.0</Y></Position><Food><fX>16.0</fX><fY>16.0</fY></Food><Score>3</Score><Direction>DOWN</Direction><Position><X>5.0</X><Y>7.0</Y></Position><Food><fX>16.0</fX><fY>16.0</fY></Food><Score>3</Score><Direction>DOWN</Direction><Position><X>5.0</X><Y>8.0</Y></Position><Food><fX>16.0</fX><fY>16.0</fY></Food><Score>3</Score><Direction>DOWN</Direction><Position><X>5.0</X><Y>9.0</Y></Position><Food><fX>16.0</fX><fY>16.0</fY></Food><Score>3</Score><Direction>DOWN</Direction><Position><X>5.0</X><Y>10.0</Y></Position><Food><fX>16.0</fX><fY>16.0</fY></Food><Score>3</Score><Direction>DOWN</Direction><Position><X>5.0</X><Y>11.0</Y></Position><Food><fX>16.0</fX><fY>16.0</fY></Food><Score>3</Score><Direction>RIGHT</Direction><Position><X>5.0</X><Y>12.0</Y></Position><Food><fX>16.0</fX><fY>16.0</fY></Food><Score>3</Score><Direction>RIGHT</Direction><Position><X>6.0</X><Y>12.0</Y></Position><Food><fX>16.0</fX><fY>16.0</fY></Food><Score>3</Score><Direction>RIGHT</Direction><Position><X>7.0</X><Y>12.0</Y></Position><Food><fX>16.0</fX><fY>16.0</fY></Food><Score>3</Score><Direction>RIGHT</Direction><Position><X>8.0</X><Y>12.0</Y></Position><Food><fX>16.0</fX><fY>16.0</fY></Food><Score>3</Score><Direction>RIGHT</Direction><Position><X>9.0</X><Y>12.0</Y></Position><Food><fX>16.0</fX><fY>16.0</fY></Food><Score>3</Score><Direction>RIGHT</Direction><Position><X>10.0</X><Y>12.0</Y></Position><Food><fX>16.0</fX><fY>16.0</fY></Food><Score>3</Score><Direction>RIGHT</Direction><Position><X>11.0</X><Y>12.0</Y></Position><Food><fX>16.0</fX><fY>16.0</fY></Food><Score>3</Score><Direction>RIGHT</Direction><Position><X>12.0</X><Y>12.0</Y></Position><Food><fX>16.0</fX><fY>16.0</fY></Food><Score>3</Score><Direction>RIGHT</Direction><Position><X>13.0</X><Y>12.0</Y></Position><Food><fX>16.0</fX><fY>16.0</fY></Food><Score>3</Score><Direction>RIGHT</Direction><Position><X>14.0</X><Y>12.0</Y></Position><Food><fX>16.0</fX><fY>16.0</fY></Food><Score>3</Score><Direction>RIGHT</Direction><Position><X>15.0</X><Y>12.0</Y></Position><Food><fX>16.0</fX><fY>16.0</fY></Food><Score>3</Score><Direction>RIGHT</Direction><Position><X>16.0</X><Y>12.0</Y></Position><Food><fX>16.0</fX><fY>16.0</fY></Food><Score>3</Score><Direction>DOWN</Direction><Position><X>17.0</X><Y>12.0</Y></Position><Food><fX>16.0</fX><fY>16.0</fY></Food><Score>3</Score><Direction>DOWN</Direction><Position><X>17.0</X><Y>13.0</Y></Position><Food><fX>16.0</fX><fY>16.0</fY></Food><Score>3</Score><Direction>DOWN</Direction><Position><X>17.0</X><Y>14.0</Y></Position><Food><fX>16.0</fX><fY>16.0</fY></Food><Score>3</Score><Direction>DOWN</Direction><Position><X>17.0</X><Y>15.0</Y></Position><Food><fX>16.0</fX><fY>16.0</fY></Food><Score>3</Score><Direction>LEFT</Direction><Position><X>17.0</X><Y>16.0</Y></Position><Food><fX>16.0</fX><fY>10.0</fY></Food><Score>3</Score><Direction>LEFT</Direction><Position><X>16.0</X><Y>16.0</Y></Position><Food><fX>16.0</fX><fY>10.0</fY></Food><Score>4</Score><Direction>LEFT</Direction><Position><X>15.0</X><Y>16.0</Y></Position><Food><fX>16.0</fX><fY>10.0</fY></Food><Score>4</Score><Direction>LEFT</Direction><Position><X>14.0</X><Y>16.0</Y></Position><Food><fX>16.0</fX><fY>10.0</fY></Food><Score>4</Score><Direction>UP</Direction><Position><X>13.0</X><Y>16.0</Y></Position><Food><fX>16.0</fX><fY>10.0</fY></Food><Score>4</Score><Direction>UP</Direction><Position><X>13.0</X><Y>15.0</Y></Position><Food><fX>16.0</fX><fY>10.0</fY></Food><Score>4</Score><Direction>UP</Direction><Position><X>13.0</X><Y>14.0</Y></Position><Food><fX>16.0</fX><fY>10.0</fY></Food><Score>4</Score><Direction>RIGHT</Direction><Position><X>13.0</X><Y>13.0</Y></Position><Food><fX>16.0</fX><fY>10.0</fY></Food><Score>4</Score><Direction>RIGHT</Direction><Position><X>14.0</X><Y>13.0</Y></Position><Food><fX>16.0</fX><fY>10.0</fY></Food><Score>4</Score><Direction>RIGHT</Direction><Position><X>15.0</X><Y>13.0</Y></Position><Food><fX>16.0</fX><fY>10.0</fY></Food><Score>4</Score><Direction>RIGHT</Direction><Position><X>16.0</X><Y>13.0</Y></Position><Food><fX>16.0</fX><fY>10.0</fY></Food><Score>4</Score><Direction>UP</Direction><Position><X>17.0</X><Y>13.0</Y></Position><Food><fX>16.0</fX><fY>10.0</fY></Food><Score>4</Score><Direction>UP</Direction><Position><X>17.0</X><Y>12.0</Y></Position><Food><fX>16.0</fX><fY>10.0</fY></Food><Score>4</Score><Direction>UP</Direction><Position><X>17.0</X><Y>11.0</Y></Position><Food><fX>16.0</fX><fY>10.0</fY></Food><Score>4</Score><Direction>LEFT</Direction><Position><X>17.0</X><Y>10.0</Y></Position><Food><fX>17.0</fX><fY>18.0</fY></Food><Score>4</Score><Direction>LEFT</Direction><Position><X>16.0</X><Y>10.0</Y></Position><Food><fX>17.0</fX><fY>18.0</fY></Food><Score>5</Score><Direction>LEFT</Direction><Position><X>15.0</X><Y>10.0</Y></Position><Food><fX>17.0</fX><fY>18.0</fY></Food><Score>5</Score><Direction>UP</Direction><Position><X>14.0</X><Y>10.0</Y></Position><Food><fX>17.0</fX><fY>18.0</fY></Food><Score>5</Score><Direction>UP</Direction><Position><X>14.0</X><Y>9.0</Y></Position><Food><fX>17.0</fX><fY>18.0</fY></Food><Score>5</Score><Direction>UP</Direction><Position><X>14.0</X><Y>8.0</Y></Position><Food><fX>17.0</fX><fY>18.0</fY></Food><Score>5</Score><Direction>RIGHT</Direction><Position><X>14.0</X><Y>7.0</Y></Position><Food><fX>17.0</fX><fY>18.0</fY></Food><Score>5</Score><Direction>RIGHT</Direction><Position><X>15.0</X><Y>7.0</Y></Position><Food><fX>17.0</fX><fY>18.0</fY></Food><Score>5</Score><Direction>RIGHT</Direction><Position><X>16.0</X><Y>7.0</Y></Position><Food><fX>17.0</fX><fY>18.0</fY></Food><Score>5</Score><Direction>RIGHT</Direction><Position><X>17.0</X><Y>7.0</Y></Position><Food><fX>17.0</fX><fY>18.0</fY></Food><Score>5</Score><Direction>RIGHT</Direction><Position><X>18.0</X><Y>7.0</Y></Position><Food><fX>17.0</fX><fY>18.0</fY></Food><Score>5</Score><Direction>RIGHT</Direction></Snake>